version.py
vertexai-1.71.0.dist-info/LICENSE
vertexai-1.71.0.dist-info/METADATA
vertexai-1.71.0.dist-info/WHEEL
vertexai-1.71.0.dist-info/top_level.txt
vertexai-1.71.0.dist-info/RECORD
